Metadata-Version: 1.0
Name: simple-table
Version: 0.0.2
Summary: A very very very basic terminal table.
Home-page: https://github.com/Frederick-S/simple-table
Author: UNKNOWN
Author-email: UNKNOWN
License: UNKNOWN
Platform: UNKNOWN
